<Alloy>
	<View class="container vertical_layout" backgroundImage='icons/distress_bg.png'>
		<View id="lasvegas" class="absolute_layout options_view padding_top">
			<Label class="options_lbl knowYourProduct touch_false" id="lblBands" text="L('lasvegas').toUpperCase()"></Label>
		</View>
		<View id="denver" class="absolute_layout options_view padding_top">
			<Label class="options_lbl knowYourProduct touch_false" id="lblEvents" text="L('denver').toUpperCase()"></Label>
		</View>
		<View id="asburypark" class="absolute_layout options_view padding_top">
			<Label class="options_lbl knowYourProduct touch_false" id="lblSchedule" text="L('asburypark').toUpperCase()"></Label>
		</View>
	</View>
</Alloy>